ibmBluegroup/__init__.py
ibmBluegroup/ibmBluegroup.py
ibmBluegroup-1.5.dist-info/DESCRIPTION.rst
ibmBluegroup-1.5.dist-info/METADATA
ibmBluegroup-1.5.dist-info/RECORD
ibmBluegroup-1.5.dist-info/WHEEL
ibmBluegroup-1.5.dist-info/metadata.json
ibmBluegroup-1.5.dist-info/top_level.txt
